[
{
  "model": "auth.group",
  "pk": 1,
  "fields": {
    "name": "admins",
    "permissions": [
      [
        "add_car",
        "webapp",
        "car"
      ],
      [
        "delete_car",
        "webapp",
        "car"
      ],
      [
        "add_photo",
        "webapp",
        "photo"
      ]
    ]
  }
},
{
  "model": "webapp.car",
  "pk": 1,
  "fields": {
    "model": "Gazelle",
    "model_en": "Gazelle",
    "model_ru": "Газель",
    "model_kz": "Газэль",
    "volume": "2.90",
    "year": "2005-10-25",
    "fuel": "Benzin",
    "fuel_en": "Benzin",
    "fuel_ru": "Бензин",
    "fuel_kz": "Бензын",
    "platform": 2
  }
},
{
  "model": "webapp.car",
  "pk": 2,
  "fields": {
    "model": "Gazelle",
    "model_en": "Gazelle",
    "model_ru": "Газель",
    "model_kz": "Газэль",
    "volume": "2.90",
    "year": "2013-10-25",
    "fuel": "Benzin",
    "fuel_en": "Benzin",
    "fuel_ru": "Бензин",
    "fuel_kz": "Бензын",
    "platform": 1
  }
},
{
  "model": "webapp.car",
  "pk": 3,
  "fields": {
    "model": "Gazelle",
    "model_en": "Gazelle",
    "model_ru": "Газель",
    "model_kz": "Газэль",
    "volume": "2.90",
    "year": "2011-10-25",
    "fuel": "Benzin",
    "fuel_en": "Benzin",
    "fuel_ru": "Бензин",
    "fuel_kz": "Бензын",
    "platform": 1
  }
},
{
  "model": "webapp.car",
  "pk": 4,
  "fields": {
    "model": "Gazelle",
    "model_en": "Gazelle",
    "model_ru": "Газель",
    "model_kz": "Газэль",
    "volume": "2.90",
    "year": "2012-10-25",
    "fuel": "Benzin",
    "fuel_en": "Benzin",
    "fuel_ru": "Бензин",
    "fuel_kz": "Бензын",
    "platform": 3
  }
},
{
  "model": "webapp.car",
  "pk": 5,
  "fields": {
    "model": "Gazelle",
    "model_en": "Gazelle",
    "model_ru": "Газель",
    "model_kz": "Газэль",
    "volume": "3.50",
    "year": "2012-10-25",
    "fuel": "Benzin",
    "fuel_en": "Benzin",
    "fuel_ru": "Бензин",
    "fuel_kz": "Бензын",
    "platform": 4
  }
},
{
  "model": "webapp.photo",
  "pk": 1,
  "fields": {
    "photo": "photos/бп.jpg",
    "car": 1
  }
},
{
  "model": "webapp.photo",
  "pk": 2,
  "fields": {
    "photo": "photos/бз.jpg",
    "car": 1
  }
},
{
  "model": "webapp.photo",
  "pk": 3,
  "fields": {
    "photo": "photos/с.jpg",
    "car": 1
  }
},
{
  "model": "webapp.photo",
  "pk": 4,
  "fields": {
    "photo": "photos/ф.п.jpg",
    "car": 4
  }
},
{
  "model": "webapp.photo",
  "pk": 5,
  "fields": {
    "photo": "photos/фз.jpg",
    "car": 4
  }
},
{
  "model": "webapp.photo",
  "pk": 6,
  "fields": {
    "photo": "photos/с1.jpg",
    "car": 4
  }
},
{
  "model": "webapp.photo",
  "pk": 7,
  "fields": {
    "photo": "photos/цп.jpg",
    "car": 2
  }
},
{
  "model": "webapp.photo",
  "pk": 8,
  "fields": {
    "photo": "photos/цз.jpg",
    "car": 2
  }
},
{
  "model": "webapp.photo",
  "pk": 9,
  "fields": {
    "photo": "photos/с2.jpg",
    "car": 2
  }
},
{
  "model": "webapp.photo",
  "pk": 10,
  "fields": {
    "photo": "photos/цп1.jpg",
    "car": 3
  }
},
{
  "model": "webapp.photo",
  "pk": 11,
  "fields": {
    "photo": "photos/цз1.jpg",
    "car": 3
  }
},
{
  "model": "webapp.photo",
  "pk": 12,
  "fields": {
    "photo": "photos/с3.jpg",
    "car": 3
  }
},
{
  "model": "webapp.photo",
  "pk": 13,
  "fields": {
    "photo": "photos/эп.jpg",
    "car": 5
  }
},
{
  "model": "webapp.photo",
  "pk": 14,
  "fields": {
    "photo": "photos/эз.jpg",
    "car": 5
  }
},
{
  "model": "webapp.photo",
  "pk": 15,
  "fields": {
    "photo": "photos/с4.jpg",
    "car": 5
  }
},
{
  "model": "webapp.platform",
  "pk": 1,
  "fields": {
    "name": "Цельнометаллическая",
    "length": 3100,
    "width": 1900,
    "height": 2200
  }
},
{
  "model": "webapp.platform",
  "pk": 2,
  "fields": {
    "name": "Борт (удлиненный)",
    "length": 4200,
    "width": 2056,
    "height": 1800
  }
},
{
  "model": "webapp.platform",
  "pk": 3,
  "fields": {
    "name": "Еврофургон",
    "length": 4200,
    "width": 2100,
    "height": 2250
  }
},
{
  "model": "webapp.platform",
  "pk": 4,
  "fields": {
    "name": "Эвакуатор",
    "length": 4500,
    "width": 2200,
    "height": 1500
  }
},
{
  "model": "auth.user",
  "pk": 1,
  "fields": {
    "password": "pbkdf2_sha256$260000$UyCf8jy8BHe8Z2Rf7y3XxT$xuG7VC7IOD2BaaA2J0ZUo3vX5/LkaKCDca85E7Db0WY=",
    "last_login": "2021-12-02T11:04:36.910Z",
    "is_superuser": true,
    "username": "admin",
    "first_name": "admin",
    "last_name": "admin",
    "email": "admin@admin.com",
    "is_staff": true,
    "is_active": true,
    "date_joined": "2021-11-03T09:17:03Z",
    "groups": [],
    "user_permissions": []
  }
},
{
  "model": "auth.user",
  "pk": 2,
  "fields": {
    "password": "pbkdf2_sha256$260000$HMPRESy0bTiaaTPlr77mSo$grzEhNIO1norvZMaICgXPQlgpTBtwGqimuUbeZuJr3E=",
    "last_login": "2021-11-03T14:38:59.120Z",
    "is_superuser": false,
    "username": "Artyom",
    "first_name": "Артем",
    "last_name": "Хван",
    "email": "hvanartem291@gmail.com",
    "is_staff": false,
    "is_active": true,
    "date_joined": "2021-11-03T13:38:21.349Z",
    "groups": [],
    "user_permissions": []
  }
},
{
  "model": "auth.user",
  "pk": 3,
  "fields": {
    "password": "pbkdf2_sha256$260000$mIxXY3JhtifCcvHrmxmPET$56shFRmX3WRdW+esJtjObM/2uSBg0JWMWWrUK4oJIag=",
    "last_login": "2021-11-03T14:38:41.517Z",
    "is_superuser": false,
    "username": "CarMixin",
    "first_name": "Mixin",
    "last_name": "Car",
    "email": "Car@as.asd",
    "is_staff": false,
    "is_active": true,
    "date_joined": "2021-11-03T14:26:01Z",
    "groups": [
      [
        "admins"
      ]
    ],
    "user_permissions": [
      [
        "add_car",
        "webapp",
        "car"
      ],
      [
        "delete_car",
        "webapp",
        "car"
      ],
      [
        "add_photo",
        "webapp",
        "photo"
      ]
    ]
  }
},
{
  "model": "webapp.review",
  "pk": 1,
  "fields": {
    "car": 3,
    "author": [
      "admin"
    ],
    "text": "ТурбоПушка",
    "created_at": "2021-11-03T10:28:23.209Z",
    "update_at": "2021-11-03T10:28:23.209Z"
  }
},
{
  "model": "webapp.review",
  "pk": 2,
  "fields": {
    "car": 3,
    "author": [
      "Artyom"
    ],
    "text": "Хороший машин",
    "created_at": "2021-11-03T13:47:04.351Z",
    "update_at": "2021-11-03T13:47:04.351Z"
  }
},
{
  "model": "webapp.client",
  "pk": 2,
  "fields": {
    "author": [
      "admin"
    ],
    "phone": "+12125552368",
    "email": "hvanartem291@gmail.com",
    "message": "dsvrtvf34",
    "created_at": "2021-12-02T12:31:00.005Z"
  }
},
{
  "model": "accounts.profile",
  "pk": 1,
  "fields": {
    "user": [
      "admin"
    ],
    "about_me": "dsfv",
    "avatar": "",
    "birth": "2011-11-11"
  }
},
{
  "model": "accounts.profile",
  "pk": 2,
  "fields": {
    "user": [
      "Artyom"
    ],
    "about_me": "Клиент1",
    "avatar": "user_pics/1586360148_youloveit_ru_bill_gravity_falls_na_avu11.jpg",
    "birth": "2011-11-11"
  }
},
{
  "model": "accounts.profile",
  "pk": 3,
  "fields": {
    "user": [
      "CarMixin"
    ],
    "about_me": null,
    "avatar": "",
    "birth": null
  }
}
]
